cabby/__init__.py
cabby/_version.py
cabby/abstract.py
cabby/client10.py
cabby/client11.py
cabby/constants.py
cabby/converters.py
cabby/dispatcher.py
cabby/entities.py
cabby/exceptions.py
cabby/utils.py
cabby/cli/__init__.py
cabby/cli/collections.py
cabby/cli/commons.py
cabby/cli/discovery.py
cabby/cli/poll.py
cabby/cli/proxy.py
cabby/cli/push.py
cabby/cli/subscriptions.py
cabby-0.1.23.dist-info/LICENSE.rst
cabby-0.1.23.dist-info/METADATA
cabby-0.1.23.dist-info/WHEEL
cabby-0.1.23.dist-info/entry_points.txt
cabby-0.1.23.dist-info/top_level.txt
cabby-0.1.23.dist-info/RECORD
