Metadata-Version: 2.1
Name: cabby
Version: 0.1.23
Summary: TAXII client library
Home-page: https://github.com/EclecticIQ/cabby/
Author: EclecticIQ
Author-email: cabby@eclecticiq.com
License: BSD License
Platform: UNKNOWN
Classifier: Development Status :: 4 - Beta
Classifier: Intended Audience :: Developers
Classifier: Intended Audience :: Information Technology
Classifier: License :: OSI Approved :: BSD License
Classifier: Programming Language :: Python
Classifier: Programming Language :: Python :: 2.7
Classifier: Programming Language :: Python :: 3.4
Classifier: Topic :: Internet
Classifier: Topic :: Security
Classifier: Topic :: Software Development :: Libraries :: Python Modules
Requires-Dist: six
Requires-Dist: libtaxii (>=1.1.111)
Requires-Dist: colorlog
Requires-Dist: pytz (>=2017.2)
Requires-Dist: furl (>=0.4.7)
Requires-Dist: requests (>=2.7.0)
